setup.py
jsonxmlsatsiuk2.egg-info/PKG-INFO
jsonxmlsatsiuk2.egg-info/SOURCES.txt
jsonxmlsatsiuk2.egg-info/dependency_links.txt
jsonxmlsatsiuk2.egg-info/jsonxmlsatsiuk2-0.1.2.tar.gz
jsonxmlsatsiuk2.egg-info/requires.txt
jsonxmlsatsiuk2.egg-info/top_level.txt
serializers/__init__.py
serializers/consts.py
serializers/factory.py
serializers/packing_tool.py
serializers/serializer.py
serializers/serializer_json.py
serializers/serializer_xml.py
test/test_value.py
test/tests.py