Metadata-Version: 2.1
Name: jsonxmlsatsiuk2
Version: 0.1.2
Summary: Library for python (de)serialization in Json and Xml
Home-page: https://github.com/panton8/igi-labs/tree/lab3
Author: stady09
Author-email: stassatsiukgg@gmail.com
License: MIT
Platform: UNKNOWN
Classifier: Intended Audience :: Developers
Classifier: Programming Language :: Python :: 3.10
Classifier: Operating System :: OS Independent
